{
  "numero": "7523",
  "date": "2026-06-24",
  "titre": "l'amendement n° 834 de M. Trébuchet à l’article 4 de la proposition de loi relative au droit à l’aide à mourir (nouvelle lecture).",
  "dossier": "Fin de vie",
  "dossierRef": "DLR5L17N51670",
  "typeVote": "scrutin public ordinaire",
  "resultat": "rejeté",
  "votants": 163,
  "pour": 62,
  "contre": 98,
  "abstentions": 3,
  "parGroupe": [
    {
      "groupe": "PO845401",
      "position": "pour",
      "pour": 41,
      "contre": 3,
      "abstentions": 1
    },
    {
      "groupe": "PO845407",
      "position": "contre",
      "pour": 2,
      "contre": 23,
      "abstentions": 0
    },
    {
      "groupe": "PO845413",
      "position": "contre",
      "pour": 0,
      "contre": 19,
      "abstentions": 0
    },
    {
      "groupe": "PO845419",
      "position": "contre",
      "pour": 0,
      "contre": 28,
      "abstentions": 0
    },
    {
      "groupe": "PO845425",
      "position": "pour",
      "pour": 12,
      "contre": 0,
      "abstentions": 0
    },
    {
      "groupe": "PO845439",
      "position": "contre",
      "pour": 0,
      "contre": 7,
      "abstentions": 0
    },
    {
      "groupe": "PO845454",
      "position": "contre",
      "pour": 0,
      "contre": 7,
      "abstentions": 0
    },
    {
      "groupe": "PO845470",
      "position": "contre",
      "pour": 0,
      "contre": 7,
      "abstentions": 1
    },
    {
      "groupe": "PO845485",
      "position": "contre",
      "pour": 0,
      "contre": 2,
      "abstentions": 1
    },
    {
      "groupe": "PO845514",
      "position": "contre",
      "pour": 0,
      "contre": 1,
      "abstentions": 0
    },
    {
      "groupe": "PO872880",
      "position": "pour",
      "pour": 7,
      "contre": 0,
      "abstentions": 0
    },
    {
      "groupe": "PO840056",
      "position": "contre",
      "pour": 0,
      "contre": 1,
      "abstentions": 0
    }
  ],
  "votesIndividuels": [
    {
      "depute": "PA796118",
      "position": "pour"
    },
    {
      "depute": "PA794434",
      "position": "pour"
    },
    {
      "depute": "PA841131",
      "position": "pour"
    },
    {
      "depute": "PA793182",
      "position": "pour"
    },
    {
      "depute": "PA793134",
      "position": "pour"
    },
    {
      "depute": "PA840075",
      "position": "pour"
    },
    {
      "depute": "PA794198",
      "position": "pour"
    },
    {
      "depute": "PA793548",
      "position": "pour"
    },
    {
      "depute": "PA795644",
      "position": "pour"
    },
    {
      "depute": "PA794762",
      "position": "pour"
    },
    {
      "depute": "PA793146",
      "position": "pour"
    },
    {
      "depute": "PA840143",
      "position": "pour"
    },
    {
      "depute": "PA794678",
      "position": "pour"
    },
    {
      "depute": "PA841139",
      "position": "pour"
    },
    {
      "depute": "PA796034",
      "position": "pour"
    },
    {
      "depute": "PA793102",
      "position": "pour"
    },
    {
      "depute": "PA793362",
      "position": "pour"
    },
    {
      "depute": "PA842097",
      "position": "pour"
    },
    {
      "depute": "PA794894",
      "position": "pour"
    },
    {
      "depute": "PA842255",
      "position": "pour"
    },
    {
      "depute": "PA841575",
      "position": "pour"
    },
    {
      "depute": "PA841451",
      "position": "pour"
    },
    {
      "depute": "PA795900",
      "position": "pour"
    },
    {
      "depute": "PA841749",
      "position": "pour"
    },
    {
      "depute": "PA841837",
      "position": "pour"
    },
    {
      "depute": "PA793608",
      "position": "pour"
    },
    {
      "depute": "PA793672",
      "position": "pour"
    },
    {
      "depute": "PA721932",
      "position": "pour"
    },
    {
      "depute": "PA795974",
      "position": "pour"
    },
    {
      "depute": "PA841587",
      "position": "pour"
    },
    {
      "depute": "PA841563",
      "position": "pour"
    },
    {
      "depute": "PA841825",
      "position": "pour"
    },
    {
      "depute": "PA793616",
      "position": "pour"
    },
    {
      "depute": "PA793852",
      "position": "pour"
    },
    {
      "depute": "PA840915",
      "position": "pour"
    },
    {
      "depute": "PA793656",
      "position": "pour"
    },
    {
      "depute": "PA793230",
      "position": "pour"
    },
    {
      "depute": "PA794442",
      "position": "pour"
    },
    {
      "depute": "PA841059",
      "position": "pour"
    },
    {
      "depute": "PA840745",
      "position": "pour"
    },
    {
      "depute": "PA840067",
      "position": "pour"
    },
    {
      "depute": "PA841645",
      "position": "contre"
    },
    {
      "depute": "PA793928",
      "position": "contre"
    },
    {
      "depute": "PA842073",
      "position": "contre"
    },
    {
      "depute": "PA840135",
      "position": "abstention"
    },
    {
      "depute": "PA719550",
      "position": "pour"
    },
    {
      "depute": "PA722102",
      "position": "pour"
    },
    {
      "depute": "PA721158",
      "position": "contre"
    },
    {
      "depute": "PA794330",
      "position": "contre"
    },
    {
      "depute": "PA794798",
      "position": "contre"
    },
    {
      "depute": "PA719118",
      "position": "contre"
    },
    {
      "depute": "PA720154",
      "position": "contre"
    },
    {
      "depute": "PA722366",
      "position": "contre"
    },
    {
      "depute": "PA793270",
      "position": "contre"
    },
    {
      "depute": "PA794802",
      "position": "contre"
    },
    {
      "depute": "PA794486",
      "position": "contre"
    },
    {
      "depute": "PA841801",
      "position": "contre"
    },
    {
      "depute": "PA842147",
      "position": "contre"
    },
    {
      "depute": "PA720022",
      "position": "contre"
    },
    {
      "depute": "PA719404",
      "position": "contre"
    },
    {
      "depute": "PA720446",
      "position": "contre"
    },
    {
      "depute": "PA795730",
      "position": "contre"
    },
    {
      "depute": "PA719338",
      "position": "contre"
    },
    {
      "depute": "PA759832",
      "position": "contre"
    },
    {
      "depute": "PA721916",
      "position": "contre"
    },
    {
      "depute": "PA722252",
      "position": "contre"
    },
    {
      "depute": "PA718820",
      "position": "contre"
    },
    {
      "depute": "PA795326",
      "position": "contre"
    },
    {
      "depute": "PA857021",
      "position": "contre"
    },
    {
      "depute": "PA879389",
      "position": "contre"
    },
    {
      "depute": "PA794906",
      "position": "contre"
    },
    {
      "depute": "PA842105",
      "position": "contre"
    },
    {
      "depute": "PA795318",
      "position": "contre"
    },
    {
      "depute": "PA795844",
      "position": "contre"
    },
    {
      "depute": "PA841251",
      "position": "contre"
    },
    {
      "depute": "PA794786",
      "position": "contre"
    },
    {
      "depute": "PA794870",
      "position": "contre"
    },
    {
      "depute": "PA793744",
      "position": "contre"
    },
    {
      "depute": "PA795310",
      "position": "contre"
    },
    {
      "depute": "PA720846",
      "position": "contre"
    },
    {
      "depute": "PA795108",
      "position": "contre"
    },
    {
      "depute": "PA791824",
      "position": "contre"
    },
    {
      "depute": "PA793532",
      "position": "contre"
    },
    {
      "depute": "PA795422",
      "position": "contre"
    },
    {
      "depute": "PA794686",
      "position": "contre"
    },
    {
      "depute": "PA841191",
      "position": "contre"
    },
    {
      "depute": "PA817211",
      "position": "contre"
    },
    {
      "depute": "PA796062",
      "position": "contre"
    },
    {
      "depute": "PA721062",
      "position": "contre"
    },
    {
      "depute": "PA342415",
      "position": "contre"
    },
    {
      "depute": "PA606793",
      "position": "contre"
    },
    {
      "depute": "PA841315",
      "position": "contre"
    },
    {
      "depute": "PA793394",
      "position": "contre"
    },
    {
      "depute": "PA606573",
      "position": "contre"
    },
    {
      "depute": "PA794854",
      "position": "contre"
    },
    {
      "depute": "PA842195",
      "position": "contre"
    },
    {
      "depute": "PA841665",
      "position": "contre"
    },
    {
      "depute": "PA822617",
      "position": "contre"
    },
    {
      "depute": "PA333285",
      "position": "contre"
    },
    {
      "depute": "PA840939",
      "position": "contre"
    },
    {
      "depute": "PA331973",
      "position": "contre"
    },
    {
      "depute": "PA841717",
      "position": "contre"
    },
    {
      "depute": "PA841243",
      "position": "contre"
    },
    {
      "depute": "PA774960",
      "position": "contre"
    },
    {
      "depute": "PA841091",
      "position": "contre"
    },
    {
      "depute": "PA719930",
      "position": "contre"
    },
    {
      "depute": "PA842263",
      "position": "contre"
    },
    {
      "depute": "PA841813",
      "position": "contre"
    },
    {
      "depute": "PA841853",
      "position": "contre"
    },
    {
      "depute": "PA774958",
      "position": "contre"
    },
    {
      "depute": "PA840765",
      "position": "contre"
    },
    {
      "depute": "PA841107",
      "position": "contre"
    },
    {
      "depute": "PA794270",
      "position": "contre"
    },
    {
      "depute": "PA840955",
      "position": "contre"
    },
    {
      "depute": "PA841367",
      "position": "contre"
    },
    {
      "depute": "PA342196",
      "position": "contre"
    },
    {
      "depute": "PA841327",
      "position": "contre"
    },
    {
      "depute": "PA642847",
      "position": "pour"
    },
    {
      "depute": "PA718884",
      "position": "pour"
    },
    {
      "depute": "PA774954",
      "position": "pour"
    },
    {
      "depute": "PA719968",
      "position": "pour"
    },
    {
      "depute": "PA332523",
      "position": "pour"
    },
    {
      "depute": "PA712015",
      "position": "pour"
    },
    {
      "depute": "PA794058",
      "position": "pour"
    },
    {
      "depute": "PA608416",
      "position": "pour"
    },
    {
      "depute": "PA346782",
      "position": "pour"
    },
    {
      "depute": "PA840979",
      "position": "pour"
    },
    {
      "depute": "PA842141",
      "position": "pour"
    },
    {
      "depute": "PA870009",
      "position": "pour"
    },
    {
      "depute": "PA841885",
      "position": "contre"
    },
    {
      "depute": "PA794008",
      "position": "contre"
    },
    {
      "depute": "PA841419",
      "position": "contre"
    },
    {
      "depute": "PA794022",
      "position": "contre"
    },
    {
      "depute": "PA796018",
      "position": "contre"
    },
    {
      "depute": "PA793948",
      "position": "contre"
    },
    {
      "depute": "PA2940",
      "position": "contre"
    },
    {
      "depute": "PA719024",
      "position": "contre"
    },
    {
      "depute": "PA719914",
      "position": "contre"
    },
    {
      "depute": "PA721182",
      "position": "contre"
    },
    {
      "depute": "PA719822",
      "position": "contre"
    },
    {
      "depute": "PA722162",
      "position": "contre"
    },
    {
      "depute": "PA331582",
      "position": "contre"
    },
    {
      "depute": "PA793556",
      "position": "contre"
    },
    {
      "depute": "PA332228",
      "position": "contre"
    },
    {
      "depute": "PA841431",
      "position": "contre"
    },
    {
      "depute": "PA794234",
      "position": "contre"
    },
    {
      "depute": "PA794838",
      "position": "contre"
    },
    {
      "depute": "PA795350",
      "position": "contre"
    },
    {
      "depute": "PA794518",
      "position": "contre"
    },
    {
      "depute": "PA842183",
      "position": "contre"
    },
    {
      "depute": "PA842125",
      "position": "abstention"
    },
    {
      "depute": "PA795244",
      "position": "contre"
    },
    {
      "depute": "PA793214",
      "position": "contre"
    },
    {
      "depute": "PA841359",
      "position": "abstention"
    },
    {
      "depute": "PA774962",
      "position": "contre"
    },
    {
      "depute": "PA840701",
      "position": "pour"
    },
    {
      "depute": "PA840721",
      "position": "pour"
    },
    {
      "depute": "PA793322",
      "position": "pour"
    },
    {
      "depute": "PA840773",
      "position": "pour"
    },
    {
      "depute": "PA840983",
      "position": "pour"
    },
    {
      "depute": "PA840657",
      "position": "pour"
    },
    {
      "depute": "PA841973",
      "position": "pour"
    },
    {
      "depute": "PA607193",
      "position": "contre"
    }
  ]
}